pytext/__init__.py
pytext/builtin_task.py
pytext/main.py
pytext/workflow.py
pytext/common/__init__.py
pytext/common/constants.py
pytext/common/utils.py
pytext/config/__init__.py
pytext/config/component.py
pytext/config/config_adapter.py
pytext/config/contextual_intent_slot.py
pytext/config/doc_classification.py
pytext/config/field_config.py
pytext/config/module_config.py
pytext/config/pair_classification.py
pytext/config/pytext_config.py
pytext/config/query_document_pairwise_ranking.py
pytext/config/serialize.py
pytext/config/utils.py
pytext/data/__init__.py
pytext/data/batch_sampler.py
pytext/data/bert_tensorizer.py
pytext/data/data.py
pytext/data/data_handler.py
pytext/data/dense_retrieval_tensorizer.py
pytext/data/disjoint_multitask_data.py
pytext/data/disjoint_multitask_data_handler.py
pytext/data/dynamic_pooling_batcher.py
pytext/data/packed_lm_data.py
pytext/data/roberta_tensorizer.py
pytext/data/squad_for_bert_tensorizer.py
pytext/data/squad_tensorizer.py
pytext/data/tensorizers.py
pytext/data/token_tensorizer.py
pytext/data/utils.py
pytext/data/xlm_constants.py
pytext/data/xlm_dictionary.py
pytext/data/xlm_tensorizer.py
pytext/data/data_structures/__init__.py
pytext/data/data_structures/annotation.py
pytext/data/data_structures/node.py
pytext/data/featurizer/__init__.py
pytext/data/featurizer/featurizer.py
pytext/data/featurizer/simple_featurizer.py
pytext/data/sources/__init__.py
pytext/data/sources/conllu.py
pytext/data/sources/data_source.py
pytext/data/sources/dense_retrieval.py
pytext/data/sources/pandas.py
pytext/data/sources/session.py
pytext/data/sources/squad.py
pytext/data/sources/tsv.py
pytext/data/test/__init__.py
pytext/data/test/batch_sampler_test.py
pytext/data/test/data_test.py
pytext/data/test/dynamic_pooling_batcher_test.py
pytext/data/test/pandas_data_source_test.py
pytext/data/test/round_robin_batchiterator_test.py
pytext/data/test/simple_featurizer_test.py
pytext/data/test/tensorizers_test.py
pytext/data/test/tokenizers_test.py
pytext_nlp-0.3.3.dist-info/LICENSE
pytext_nlp-0.3.3.dist-info/METADATA
pytext_nlp-0.3.3.dist-info/WHEEL
pytext_nlp-0.3.3.dist-info/entry_points.txt
pytext_nlp-0.3.3.dist-info/top_level.txt
pytext_nlp-0.3.3.dist-info/RECORD
