Metadata-Version: 2.1
Name: pytext-nlp
Version: 0.3.3
Summary: pytorch modeling framework and model zoo for text models
Home-page: https://github.com/facebookresearch/PyText
Author: Facebook
Author-email: UNKNOWN
License: BSD
Platform: UNKNOWN
Requires-Dist: absl-py (==0.9.0)
Requires-Dist: attrs (==19.3.0)
Requires-Dist: bleach (==3.1.5)
Requires-Dist: boto3 (==1.13.25)
Requires-Dist: botocore (==1.16.25)
Requires-Dist: certifi (==2020.4.5.1)
Requires-Dist: cffi (==1.14.0)
Requires-Dist: chardet (==3.0.4)
Requires-Dist: click (==7.1.2)
Requires-Dist: Cython (==0.29.19)
Requires-Dist: docutils (==0.16)
Requires-Dist: fairseq (==0.9.0)
Requires-Dist: future (==0.18.2)
Requires-Dist: fvcore (==0.1.1.post20200608)
Requires-Dist: grpcio (==1.29.0)
Requires-Dist: hypothesis (==3.88.3)
Requires-Dist: idna (==2.9)
Requires-Dist: importlib-metadata (==1.6.0)
Requires-Dist: jmespath (==0.10.0)
Requires-Dist: joblib (==0.15.1)
Requires-Dist: keyring (==21.2.1)
Requires-Dist: Markdown (==3.2.2)
Requires-Dist: more-itertools (==8.3.0)
Requires-Dist: numpy (==1.18.5)
Requires-Dist: onnx (==1.7.0)
Requires-Dist: packaging (==20.4)
Requires-Dist: pandas (==1.0.4)
Requires-Dist: Pillow (==7.1.2)
Requires-Dist: pkginfo (==1.5.0.1)
Requires-Dist: pluggy (==0.13.1)
Requires-Dist: portalocker (==1.7.0)
Requires-Dist: protobuf (==3.12.2)
Requires-Dist: py (==1.8.1)
Requires-Dist: pycparser (==2.20)
Requires-Dist: Pygments (==2.6.1)
Requires-Dist: pyparsing (==2.4.7)
Requires-Dist: pytest (==5.4.2)
Requires-Dist: python-dateutil (==2.8.0)
Requires-Dist: pytorch-dp (==0.1b1)
Requires-Dist: pytorch-pretrained-bert (==0.6.2)
Requires-Dist: pytz (==2020.1)
Requires-Dist: PyYAML (==5.3.1)
Requires-Dist: readme-renderer (==26.0)
Requires-Dist: regex (==2019.11.1)
Requires-Dist: requests (==2.23.0)
Requires-Dist: requests-toolbelt (==0.9.1)
Requires-Dist: s3transfer (==0.3.3)
Requires-Dist: sacrebleu (==1.4.10)
Requires-Dist: scipy (==1.4.1)
Requires-Dist: sentencepiece (==0.1.92)
Requires-Dist: six (==1.15.0)
Requires-Dist: tabulate (==0.8.7)
Requires-Dist: tensorboard (==1.14.0)
Requires-Dist: termcolor (==1.1.0)
Requires-Dist: torch (==1.5.0)
Requires-Dist: torchtext (==0.6.0)
Requires-Dist: torchvision (==0.6.0)
Requires-Dist: tqdm (==4.46.1)
Requires-Dist: twine (==3.1.1)
Requires-Dist: typing-extensions (==3.7.4.2)
Requires-Dist: urllib3 (==1.25.9)
Requires-Dist: wcwidth (==0.1.9)
Requires-Dist: webencodings (==0.5.1)
Requires-Dist: Werkzeug (==1.0.1)
Requires-Dist: yacs (==0.1.7)
Requires-Dist: zipp (==3.1.0)
